odoo/addons/__init__.py
odoo/addons/l10n_be_intrastat/__init__.py
odoo/addons/l10n_be_intrastat/__manifest__.py
odoo/addons/l10n_be_intrastat/data/l10n_be_intrastat_chart_data.xml
odoo/addons/l10n_be_intrastat/data/l10n_be_intrastat_transaction_codes_data.xml
odoo/addons/l10n_be_intrastat/data/l10n_be_intrastat_transport_modes_data.xml
odoo/addons/l10n_be_intrastat/data/report.intrastat.code.csv
odoo/addons/l10n_be_intrastat/doc/intrastat.rst
odoo/addons/l10n_be_intrastat/i18n/af.po
odoo/addons/l10n_be_intrastat/i18n/am.po
odoo/addons/l10n_be_intrastat/i18n/ar.po
odoo/addons/l10n_be_intrastat/i18n/bg.po
odoo/addons/l10n_be_intrastat/i18n/bn.po
odoo/addons/l10n_be_intrastat/i18n/bs.po
odoo/addons/l10n_be_intrastat/i18n/ca.po
odoo/addons/l10n_be_intrastat/i18n/cs.po
odoo/addons/l10n_be_intrastat/i18n/da.po
odoo/addons/l10n_be_intrastat/i18n/de.po
odoo/addons/l10n_be_intrastat/i18n/el.po
odoo/addons/l10n_be_intrastat/i18n/en_AU.po
odoo/addons/l10n_be_intrastat/i18n/en_GB.po
odoo/addons/l10n_be_intrastat/i18n/es.po
odoo/addons/l10n_be_intrastat/i18n/es_BO.po
odoo/addons/l10n_be_intrastat/i18n/es_CL.po
odoo/addons/l10n_be_intrastat/i18n/es_CO.po
odoo/addons/l10n_be_intrastat/i18n/es_CR.po
odoo/addons/l10n_be_intrastat/i18n/es_DO.po
odoo/addons/l10n_be_intrastat/i18n/es_EC.po
odoo/addons/l10n_be_intrastat/i18n/es_PA.po
odoo/addons/l10n_be_intrastat/i18n/es_PE.po
odoo/addons/l10n_be_intrastat/i18n/es_PY.po
odoo/addons/l10n_be_intrastat/i18n/es_VE.po
odoo/addons/l10n_be_intrastat/i18n/et.po
odoo/addons/l10n_be_intrastat/i18n/eu.po
odoo/addons/l10n_be_intrastat/i18n/fa.po
odoo/addons/l10n_be_intrastat/i18n/fi.po
odoo/addons/l10n_be_intrastat/i18n/fo.po
odoo/addons/l10n_be_intrastat/i18n/fr.po
odoo/addons/l10n_be_intrastat/i18n/fr_BE.po
odoo/addons/l10n_be_intrastat/i18n/fr_CA.po
odoo/addons/l10n_be_intrastat/i18n/gl.po
odoo/addons/l10n_be_intrastat/i18n/gu.po
odoo/addons/l10n_be_intrastat/i18n/he.po
odoo/addons/l10n_be_intrastat/i18n/hi.po
odooku_odoo_purchase-11.0.7.dist-info/LICENSE
odooku_odoo_purchase-11.0.7.dist-info/METADATA
odooku_odoo_purchase-11.0.7.dist-info/WHEEL
odooku_odoo_purchase-11.0.7.dist-info/top_level.txt
odooku_odoo_purchase-11.0.7.dist-info/RECORD
